include/nanoflann.hpp
include/napf.hpp
lib/cmake/napf/napfConfig.cmake
lib/cmake/napf/napfConfigVersion.cmake
lib/cmake/napf/napfTargets.cmake
napf/__init__.py
napf/_napf.pyd
napf/_version.py
napf/base.py
napf-0.1.0.dist-info/METADATA
napf-0.1.0.dist-info/WHEEL
napf-0.1.0.dist-info/licenses/LICENSE
napf-0.1.0.dist-info/RECORD
