Metadata-Version: 2.1
Name: napf
Version: 0.1.0
Summary: nanoflann python bindings for kdtree with multithreaded queries
Author-Email: Jaewook Lee <jaewooklee042@gmail.com>
License: MIT License
Classifier: Development Status :: 4 - Beta
Classifier: License :: OSI Approved :: MIT License
Classifier: Programming Language :: Python
Classifier: Natural Language :: English
Classifier: Topic :: Scientific/Engineering
Project-URL: Homepage, https://github.com/tataratat/napf
Requires-Python: >=3.7
Requires-Dist: numpy
